spicemanip/__init__.py
spicemanip-0.1.7.dist-info/AUTHORS.rst
spicemanip-0.1.7.dist-info/LICENSE
spicemanip-0.1.7.dist-info/METADATA
spicemanip-0.1.7.dist-info/WHEEL
spicemanip-0.1.7.dist-info/top_level.txt
spicemanip-0.1.7.dist-info/RECORD
