Metadata-Version: 2.1
Name: spicemanip
Version: 0.1.7
Summary: spicemanip aims to ease list and string manipulation
Home-page: https://github.com/deathbybandaid/spicemanip
Author: Sam Zick
Author-email: sam@deathbybandaid.net
License: MIT license
Keywords: spicemanip
Platform: UNKNOWN
Classifier: Development Status :: 2 - Pre-Alpha
Classifier: Intended Audience :: Developers
Classifier: License :: OSI Approved :: MIT License
Classifier: Natural Language :: English
Classifier: Programming Language :: Python :: 2
Classifier: Programming Language :: Python :: 2.7
Classifier: Programming Language :: Python :: 3
Classifier: Programming Language :: Python :: 3.4
Classifier: Programming Language :: Python :: 3.5
Classifier: Programming Language :: Python :: 3.6
Classifier: Programming Language :: Python :: 3.7
